calibpy/Aruco.py
calibpy/Calibration.py
calibpy/Camera.py
calibpy/Registration.py
calibpy/Serializer.py
calibpy/Settings.py
calibpy/Stream.py
calibpy/__init__.py
calibpy/blender_utils.py
calibpy/sandbox.py
calibpy/single_cam_workflow.py
tests/__init__.py
tests/test_Camera.py
tests/test_Serializer.py
tests/test_Settings.py
tests/test_Stream.py
tests/test_workflows.py
calibpy-1.0.0.dist-info/LICENSE.txt
calibpy-1.0.0.dist-info/METADATA
calibpy-1.0.0.dist-info/WHEEL
calibpy-1.0.0.dist-info/top_level.txt
calibpy-1.0.0.dist-info/RECORD
