Metadata-Version: 2.1
Name: calibpy
Version: 1.0.0
Summary: A simple camera calibration toolkit based on opencv to do intrinsic and extrinsic camera calibration as well as depth registration tasks.
Home-page: https://github.com/artificialpixels/calibpy
Author: Artificial Pixels
Author-email: artificial.pixels@gmail.com
Project-URL: Bug Tracker, https://github.com/artificialpixels/calibpy/issues
Project-URL: repository, https://github.com/artificialpixels/calibpy
Classifier: Programming Language :: Python :: 3
Classifier: License :: OSI Approved :: MIT License
Classifier: Operating System :: OS Independent
Requires-Python: >=3.9
License-File: LICENSE.txt
